aiy/__init__.py
aiy/_buzzer.py
aiy/board.py
aiy/leds.py
aiy/pins.py
aiy/toneplayer.py
aiy/trackplayer.py
aiy/vision/__init__.py
aiy/vision/_spicomm.py
aiy/vision/_transport.py
aiy/vision/annotator.py
aiy/vision/inference.py
aiy/vision/models/__init__.py
aiy/vision/models/dish_classification.py
aiy/vision/models/dish_detection.py
aiy/vision/models/face_detection.py
aiy/vision/models/image_classification.py
aiy/vision/models/inaturalist_classification.py
aiy/vision/models/object_detection.py
aiy/vision/models/utils.py
aiy/vision/proto/__init__.py
aiy/vision/proto/protocol_pb2.py
aiy/voice/__init__.py
aiy/voice/audio.py
aiy/voice/tts.py
aiy_projects_python-1.4.dist-info/LICENSE
aiy_projects_python-1.4.dist-info/METADATA
aiy_projects_python-1.4.dist-info/WHEEL
aiy_projects_python-1.4.dist-info/top_level.txt
aiy_projects_python-1.4.dist-info/RECORD
